README.md
setup.py
free_bobux.egg-info/PKG-INFO
free_bobux.egg-info/SOURCES.txt
free_bobux.egg-info/dependency_links.txt
free_bobux.egg-info/entry_points.txt
free_bobux.egg-info/requires.txt
free_bobux.egg-info/top_level.txt
rickroll/__init__.py
rickroll/rick.py