Metadata-Version: 2.1
Name: free-bobux
Version: 420.69.0
Summary: GeT fReE rObUx NoW!!!!
Home-page: https://www.youtube.com/watch?v=dQw4w9WgXcQ
Author: Richard Astley
Author-email: rick.astley@gmail.com
